<?xml version="1.0"?>
<FmtMappingTable Version="2">
  <Head>
    <SourceCodeList>Bright</SourceCodeList>
    <SourceCodeListVersion>2.0.6</SourceCodeListVersion>
    <TargetCodeList>V05</TargetCodeList>
    <TargetCodeListVersion>4.4.1.40</TargetCodeListVersion>
    <CodeTrimmingOnSource>false</CodeTrimmingOnSource>
    <ImportToUnmappedSources>Ignore</ImportToUnmappedSources>
    <ImportToLockedTargets>Warning</ImportToLockedTargets>
    <ImportToUnknownTargets>Warning</ImportToUnknownTargets>
    <EraseAllTargets>false</EraseAllTargets>
    <EnableCalculatedSourceAccounts>false</EnableCalculatedSourceAccounts>
    <AcceptTimeLineTargetAccounts>false</AcceptTimeLineTargetAccounts>
    <AcceptXbrlSumTargetAccounts>true</AcceptXbrlSumTargetAccounts>
    <MultiLevelDataInSource>true</MultiLevelDataInSource>
    <DCSignedSourceValues>false</DCSignedSourceValues>
    <Creator>FinanMappingTool</Creator>
    <CreatorVersion>4.2.9</CreatorVersion>
    <User>b.kottier</User>
    <UpdateDate>2015-07-20</UpdateDate>
    <TableVersion>01.00.003</TableVersion>
    <Notes></Notes>
    <StatusCode>0</StatusCode>
  </Head>
  <Versions>
    <Version>
      <VersionCode>01.00.000</VersionCode>
      <Date>2015-06-24</Date>
      <Author>b.kottier</Author>
      <Changes>Created</Changes>
    </Version>
    <Version>
      <VersionCode>01.00.002</VersionCode>
      <Date>2015-07-14</Date>
      <Author>b.kottier</Author>
      <Changes>Winkelbeoordelingen toegevoegd</Changes>
    </Version>
    <Version>
      <VersionCode>01.00.003</VersionCode>
      <Date>2015-07-14</Date>
      <Author>b.kottier</Author>
      <Changes>maps benchmark class</Changes>
    </Version>
  </Versions>
  <OpenFiles>
    <OpenFile Type="Source">..\..\..\Users\b.kottier.FINAN\Desktop\40050.xml</OpenFile>
    <OpenFile Type="Target">..\FMT4 Models\Finan\V05_BBI.Fmt4Model.xml</OpenFile>
  </OpenFiles>
  <TargetValues>
    <TargetValue>
      <TargetCode>ChangesInEquityApproved</TargetCode>
      <TargetCodeAlias></TargetCodeAlias>
      <TargetFinanVarName>ChangesInEquityApproved</TargetFinanVarName>
      <TargetDataType>Boolean</TargetDataType>
      <Value>1</Value>
      <Priority>40</Priority>
      <Add>false</Add>
      <TargetDepth>40</TargetDepth>
      <FormulaSet>NoTrend</FormulaSet>
      <Condition></Condition>
      <Comment></Comment>
    </TargetValue>
    <TargetValue>
      <TargetCode>SharedCapitalPreferenceShares</TargetCode>
      <TargetCodeAlias></TargetCodeAlias>
      <TargetFinanVarName>SharedCapitalPreferenceShares</TargetFinanVarName>
      <TargetDataType>Monetary</TargetDataType>
      <Value>0</Value>
      <Priority>50</Priority>
      <Add>true</Add>
      <TargetDepth>50</TargetDepth>
      <FormulaSet>NoTrend</FormulaSet>
      <Condition></Condition>
      <Comment></Comment>
    </TargetValue>
  </TargetValues>
  <TupleEntries/>
  <Entries>
    <Entry>
      <SourceCode>NettoOmzet</SourceCode>
      <SourceCodeAlias></SourceCodeAlias>
      <SourceFinanVarName>NettoOmzet</SourceFinanVarName>
      <TargetCode>NetSales</TargetCode>
      <TargetCodeAlias></TargetCodeAlias>
      <TargetFinanVarName>NetSales</TargetFinanVarName>
      <TargetDataType>Monetary</TargetDataType>
      <Factor>1</Factor>
      <Priority>30</Priority>
      <Add>true</Add>
      <TargetDepth>30</TargetDepth>
      <Condition></Condition>
      <Comment></Comment>
    </Entry>
    <Entry>
      <SourceCode>Inkopen</SourceCode>
      <SourceCodeAlias></SourceCodeAlias>
      <SourceFinanVarName>Inkopen</SourceFinanVarName>
      <TargetCode>TradeCostOfSales</TargetCode>
      <TargetCodeAlias></TargetCodeAlias>
      <TargetFinanVarName>TradeCostOfSales</TargetFinanVarName>
      <TargetDataType>Monetary</TargetDataType>
      <Factor>-1</Factor>
      <Priority>40</Priority>
      <Add>true</Add>
      <TargetDepth>40</TargetDepth>
      <Condition></Condition>
      <Comment></Comment>
    </Entry>
    <Entry>
      <SourceCode>Omzetbonus</SourceCode>
      <SourceCodeAlias></SourceCodeAlias>
      <SourceFinanVarName>Omzetbonus</SourceFinanVarName>
      <TargetCode>PurchaseDiscountsAndBonuses</TargetCode>
      <TargetCodeAlias></TargetCodeAlias>
      <TargetFinanVarName>PurchaseDiscountsAndBonuses</TargetFinanVarName>
      <TargetDataType>Monetary</TargetDataType>
      <Factor>1</Factor>
      <Priority>40</Priority>
      <Add>true</Add>
      <TargetDepth>40</TargetDepth>
      <Condition></Condition>
      <Comment></Comment>
    </Entry>
    <Entry>
      <SourceCode>Voorraadmutatie</SourceCode>
      <SourceCodeAlias></SourceCodeAlias>
      <SourceFinanVarName>Voorraadmutatie</SourceFinanVarName>
      <TargetCode>ChangeInInventories</TargetCode>
      <TargetCodeAlias></TargetCodeAlias>
      <TargetFinanVarName>ChangeInInventories</TargetFinanVarName>
      <TargetDataType>Monetary</TargetDataType>
      <Factor>1</Factor>
      <Priority>30</Priority>
      <Add>true</Add>
      <TargetDepth>30</TargetDepth>
      <Condition></Condition>
      <Comment></Comment>
    </Entry>
    <Entry>
      <SourceCode>OverigeOmzetten</SourceCode>
      <SourceCodeAlias></SourceCodeAlias>
      <SourceFinanVarName>OverigeOmzetten</SourceFinanVarName>
      <TargetCode>OtherOperatingIncome</TargetCode>
      <TargetCodeAlias></TargetCodeAlias>
      <TargetFinanVarName>OtherOperatingIncome</TargetFinanVarName>
      <TargetDataType>Monetary</TargetDataType>
      <Factor>1</Factor>
      <Priority>30</Priority>
      <Add>true</Add>
      <TargetDepth>30</TargetDepth>
      <Condition></Condition>
      <Comment></Comment>
    </Entry>
    <Entry>
      <SourceCode>Personeelskosten</SourceCode>
      <SourceCodeAlias></SourceCodeAlias>
      <SourceFinanVarName>Personeelskosten</SourceFinanVarName>
      <TargetCode>PersonnelExpenses</TargetCode>
      <TargetCodeAlias></TargetCodeAlias>
      <TargetFinanVarName>PersonnelExpenses</TargetFinanVarName>
      <TargetDataType>Monetary</TargetDataType>
      <Factor>-1</Factor>
      <Priority>40</Priority>
      <Add>true</Add>
      <TargetDepth>40</TargetDepth>
      <Condition></Condition>
      <Comment></Comment>
    </Entry>
    <Entry>
      <SourceCode>FinancieleBatenLasten</SourceCode>
      <SourceCodeAlias></SourceCodeAlias>
      <SourceFinanVarName>FinancieleBatenLasten</SourceFinanVarName>
      <TargetCode>OtherInterestExpenses</TargetCode>
      <TargetCodeAlias></TargetCodeAlias>
      <TargetFinanVarName>OtherInterestExpenses</TargetFinanVarName>
      <TargetDataType>Monetary</TargetDataType>
      <Factor>-1</Factor>
      <Priority>50</Priority>
      <Add>true</Add>
      <TargetDepth>50</TargetDepth>
      <Condition></Condition>
      <Comment></Comment>
    </Entry>
    <Entry>
      <SourceCode>BijzondereBatenLasten</SourceCode>
      <SourceCodeAlias></SourceCodeAlias>
      <SourceFinanVarName>BijzondereBatenLasten</SourceFinanVarName>
      <TargetCode>OtherExtraordinaryIncome</TargetCode>
      <TargetCodeAlias></TargetCodeAlias>
      <TargetFinanVarName>OtherExtraordinaryIncome</TargetFinanVarName>
      <TargetDataType>Monetary</TargetDataType>
      <Factor>1</Factor>
      <Priority>50</Priority>
      <Add>true</Add>
      <TargetDepth>50</TargetDepth>
      <Condition></Condition>
      <Comment></Comment>
    </Entry>
    <Entry>
      <SourceCode>BelastingenBedrijfsvoering</SourceCode>
      <SourceCodeAlias></SourceCodeAlias>
      <SourceFinanVarName>BelastingenBedrijfsvoering</SourceFinanVarName>
      <TargetCode>TaxOnProfits</TargetCode>
      <TargetCodeAlias></TargetCodeAlias>
      <TargetFinanVarName>TaxOnProfits</TargetFinanVarName>
      <TargetDataType>Monetary</TargetDataType>
      <Factor>-1</Factor>
      <Priority>30</Priority>
      <Add>true</Add>
      <TargetDepth>30</TargetDepth>
      <Condition></Condition>
      <Comment></Comment>
    </Entry>
    <Entry>
      <SourceCode>AfschrijvingVasteActiva</SourceCode>
      <SourceCodeAlias></SourceCodeAlias>
      <SourceFinanVarName>AfschrijvingVasteActiva</SourceFinanVarName>
      <TargetCode>DepreciationOfAssets</TargetCode>
      <TargetCodeAlias></TargetCodeAlias>
      <TargetFinanVarName>DepreciationOfAssets</TargetFinanVarName>
      <TargetDataType>Monetary</TargetDataType>
      <Factor>-1</Factor>
      <Priority>30</Priority>
      <Add>true</Add>
      <TargetDepth>30</TargetDepth>
      <Condition></Condition>
      <Comment></Comment>
    </Entry>
    <Entry>
      <SourceCode>ImmaterieelVasteActiva</SourceCode>
      <SourceCodeAlias></SourceCodeAlias>
      <SourceFinanVarName>ImmaterieelVasteActiva</SourceFinanVarName>
      <TargetCode>IntangibleFixedAssets</TargetCode>
      <TargetCodeAlias></TargetCodeAlias>
      <TargetFinanVarName>IntangibleFixedAssets</TargetFinanVarName>
      <TargetDataType>Monetary</TargetDataType>
      <Factor>1</Factor>
      <Priority>30</Priority>
      <Add>true</Add>
      <TargetDepth>30</TargetDepth>
      <Condition></Condition>
      <Comment></Comment>
    </Entry>
    <Entry>
      <SourceCode>FinancieelVasteActiva</SourceCode>
      <SourceCodeAlias></SourceCodeAlias>
      <SourceFinanVarName>FinancieelVasteActiva</SourceFinanVarName>
      <TargetCode>FinancialFixedAssets</TargetCode>
      <TargetCodeAlias></TargetCodeAlias>
      <TargetFinanVarName>FinancialFixedAssets</TargetFinanVarName>
      <TargetDataType>Monetary</TargetDataType>
      <Factor>1</Factor>
      <Priority>30</Priority>
      <Add>true</Add>
      <TargetDepth>30</TargetDepth>
      <Condition></Condition>
      <Comment></Comment>
    </Entry>
    <Entry>
      <SourceCode>GebouwenVerbouwingen</SourceCode>
      <SourceCodeAlias></SourceCodeAlias>
      <SourceFinanVarName>GebouwenVerbouwingen</SourceFinanVarName>
      <TargetCode>TotalLandAndBuildings</TargetCode>
      <TargetCodeAlias></TargetCodeAlias>
      <TargetFinanVarName>TotalLandAndBuildings</TargetFinanVarName>
      <TargetDataType>Monetary</TargetDataType>
      <Factor>1</Factor>
      <Priority>40</Priority>
      <Add>true</Add>
      <TargetDepth>40</TargetDepth>
      <Condition></Condition>
      <Comment></Comment>
    </Entry>
    <Entry>
      <SourceCode>Machines</SourceCode>
      <SourceCodeAlias></SourceCodeAlias>
      <SourceFinanVarName>Machines</SourceFinanVarName>
      <TargetCode>TotalPlantAndEquipment</TargetCode>
      <TargetCodeAlias></TargetCodeAlias>
      <TargetFinanVarName>TotalPlantAndEquipment</TargetFinanVarName>
      <TargetDataType>Monetary</TargetDataType>
      <Factor>1</Factor>
      <Priority>40</Priority>
      <Add>true</Add>
      <TargetDepth>40</TargetDepth>
      <Condition></Condition>
      <Comment></Comment>
    </Entry>
    <Entry>
      <SourceCode>Inventaris</SourceCode>
      <SourceCodeAlias></SourceCodeAlias>
      <SourceFinanVarName>Inventaris</SourceFinanVarName>
      <TargetCode>TotalFurnitureAndFixtures</TargetCode>
      <TargetCodeAlias></TargetCodeAlias>
      <TargetFinanVarName>TotalFurnitureAndFixtures</TargetFinanVarName>
      <TargetDataType>Monetary</TargetDataType>
      <Factor>1</Factor>
      <Priority>40</Priority>
      <Add>true</Add>
      <TargetDepth>40</TargetDepth>
      <Condition></Condition>
      <Comment></Comment>
    </Entry>
    <Entry>
      <SourceCode>Vervoermiddelen</SourceCode>
      <SourceCodeAlias></SourceCodeAlias>
      <SourceFinanVarName>Vervoermiddelen</SourceFinanVarName>
      <TargetCode>TotalTransportationEquipment</TargetCode>
      <TargetCodeAlias></TargetCodeAlias>
      <TargetFinanVarName>TotalTransportationEquipment</TargetFinanVarName>
      <TargetDataType>Monetary</TargetDataType>
      <Factor>1</Factor>
      <Priority>40</Priority>
      <Add>true</Add>
      <TargetDepth>40</TargetDepth>
      <Condition></Condition>
      <Comment></Comment>
    </Entry>
    <Entry>
      <SourceCode>NettoResultaatNaBelasting</SourceCode>
      <SourceCodeAlias></SourceCodeAlias>
      <SourceFinanVarName>NettoResultaatNaBelasting</SourceFinanVarName>
      <TargetCode>RemarkImportCheckResultImport</TargetCode>
      <TargetCodeAlias></TargetCodeAlias>
      <TargetFinanVarName>RemarkImportCheckResultImport</TargetFinanVarName>
      <TargetDataType>Monetary</TargetDataType>
      <Factor>1</Factor>
      <Priority>70</Priority>
      <Add>true</Add>
      <TargetDepth>70</TargetDepth>
      <Condition></Condition>
      <Comment></Comment>
    </Entry>
    <Entry>
      <SourceCode>Voorraden</SourceCode>
      <SourceCodeAlias></SourceCodeAlias>
      <SourceFinanVarName>Voorraden</SourceFinanVarName>
      <TargetCode>Inventories</TargetCode>
      <TargetCodeAlias></TargetCodeAlias>
      <TargetFinanVarName>Inventories</TargetFinanVarName>
      <TargetDataType>Monetary</TargetDataType>
      <Factor>1</Factor>
      <Priority>30</Priority>
      <Add>true</Add>
      <TargetDepth>30</TargetDepth>
      <Condition></Condition>
      <Comment></Comment>
    </Entry>
    <Entry>
      <SourceCode>VorderingGroepsmaatschappijen</SourceCode>
      <SourceCodeAlias></SourceCodeAlias>
      <SourceFinanVarName>VorderingGroepsmaatschappijen</SourceFinanVarName>
      <TargetCode>ReceivablesGroupCompanies</TargetCode>
      <TargetCodeAlias></TargetCodeAlias>
      <TargetFinanVarName>ReceivablesGroupCompanies</TargetFinanVarName>
      <TargetDataType>Monetary</TargetDataType>
      <Factor>1</Factor>
      <Priority>40</Priority>
      <Add>true</Add>
      <TargetDepth>40</TargetDepth>
      <Condition></Condition>
      <Comment></Comment>
    </Entry>
    <Entry>
      <SourceCode>VorderingBelastingSocialeLasten</SourceCode>
      <SourceCodeAlias></SourceCodeAlias>
      <SourceFinanVarName>VorderingBelastingSocialeLasten</SourceFinanVarName>
      <TargetCode>OtherAccountsReceivable</TargetCode>
      <TargetCodeAlias></TargetCodeAlias>
      <TargetFinanVarName>OtherAccountsReceivable</TargetFinanVarName>
      <TargetDataType>Monetary</TargetDataType>
      <Factor>1</Factor>
      <Priority>40</Priority>
      <Add>true</Add>
      <TargetDepth>40</TargetDepth>
      <Condition></Condition>
      <Comment></Comment>
    </Entry>
    <Entry>
      <SourceCode>Debiteuren</SourceCode>
      <SourceCodeAlias></SourceCodeAlias>
      <SourceFinanVarName>Debiteuren</SourceFinanVarName>
      <TargetCode>TradeReceivables</TargetCode>
      <TargetCodeAlias></TargetCodeAlias>
      <TargetFinanVarName>TradeReceivables</TargetFinanVarName>
      <TargetDataType>Monetary</TargetDataType>
      <Factor>1</Factor>
      <Priority>50</Priority>
      <Add>true</Add>
      <TargetDepth>50</TargetDepth>
      <Condition></Condition>
      <Comment></Comment>
    </Entry>
    <Entry>
      <SourceCode>OverigeVorderingen</SourceCode>
      <SourceCodeAlias></SourceCodeAlias>
      <SourceFinanVarName>OverigeVorderingen</SourceFinanVarName>
      <TargetCode>OtherReceivables</TargetCode>
      <TargetCodeAlias></TargetCodeAlias>
      <TargetFinanVarName>OtherReceivables</TargetFinanVarName>
      <TargetDataType>Monetary</TargetDataType>
      <Factor>1</Factor>
      <Priority>40</Priority>
      <Add>true</Add>
      <TargetDepth>40</TargetDepth>
      <Condition></Condition>
      <Comment></Comment>
    </Entry>
    <Entry>
      <SourceCode>LiquideMiddelen</SourceCode>
      <SourceCodeAlias></SourceCodeAlias>
      <SourceFinanVarName>LiquideMiddelen</SourceFinanVarName>
      <TargetCode>CashAndEquivalents</TargetCode>
      <TargetCodeAlias></TargetCodeAlias>
      <TargetFinanVarName>CashAndEquivalents</TargetFinanVarName>
      <TargetDataType>Monetary</TargetDataType>
      <Factor>1</Factor>
      <Priority>30</Priority>
      <Add>true</Add>
      <TargetDepth>30</TargetDepth>
      <Condition></Condition>
      <Comment></Comment>
    </Entry>
    <Entry>
      <SourceCode>BalansTotaal</SourceCode>
      <SourceCodeAlias></SourceCodeAlias>
      <SourceFinanVarName>BalansTotaal</SourceFinanVarName>
      <TargetCode>RemarkImportCheckBalanceImport</TargetCode>
      <TargetCodeAlias></TargetCodeAlias>
      <TargetFinanVarName>RemarkImportCheckBalanceImport</TargetFinanVarName>
      <TargetDataType>Monetary</TargetDataType>
      <Factor>1</Factor>
      <Priority>70</Priority>
      <Add>true</Add>
      <TargetDepth>70</TargetDepth>
      <Condition></Condition>
      <Comment></Comment>
    </Entry>
    <Entry>
      <SourceCode>BankLening</SourceCode>
      <SourceCodeAlias></SourceCodeAlias>
      <SourceFinanVarName>BankLening</SourceFinanVarName>
      <TargetCode>LongTermDebts</TargetCode>
      <TargetCodeAlias></TargetCodeAlias>
      <TargetFinanVarName>LongTermDebts</TargetFinanVarName>
      <TargetDataType>Monetary</TargetDataType>
      <Factor>1</Factor>
      <Priority>40</Priority>
      <Add>true</Add>
      <TargetDepth>40</TargetDepth>
      <Condition></Condition>
      <Comment></Comment>
    </Entry>
    <Entry>
      <SourceCode>OverigeLening</SourceCode>
      <SourceCodeAlias></SourceCodeAlias>
      <SourceFinanVarName>OverigeLening</SourceFinanVarName>
      <TargetCode>LongTermDebtsOther</TargetCode>
      <TargetCodeAlias></TargetCodeAlias>
      <TargetFinanVarName>LongTermDebtsOther</TargetFinanVarName>
      <TargetDataType>Monetary</TargetDataType>
      <Factor>1</Factor>
      <Priority>40</Priority>
      <Add>true</Add>
      <TargetDepth>40</TargetDepth>
      <Condition></Condition>
      <Comment></Comment>
    </Entry>
    <Entry>
      <SourceCode>Crediteuren</SourceCode>
      <SourceCodeAlias></SourceCodeAlias>
      <SourceFinanVarName>Crediteuren</SourceFinanVarName>
      <TargetCode>TradePayables</TargetCode>
      <TargetCodeAlias></TargetCodeAlias>
      <TargetFinanVarName>TradePayables</TargetFinanVarName>
      <TargetDataType>Monetary</TargetDataType>
      <Factor>1</Factor>
      <Priority>50</Priority>
      <Add>true</Add>
      <TargetDepth>50</TargetDepth>
      <Condition></Condition>
      <Comment></Comment>
    </Entry>
    <Entry>
      <SourceCode>KorteSchuldenGroepsmaatschappijen</SourceCode>
      <SourceCodeAlias></SourceCodeAlias>
      <SourceFinanVarName>KorteSchuldenGroepsmaatschappijen</SourceFinanVarName>
      <TargetCode>CurrentAccountGroupCompanies</TargetCode>
      <TargetCodeAlias></TargetCodeAlias>
      <TargetFinanVarName>CurrentAccountGroupCompanies</TargetFinanVarName>
      <TargetDataType>Monetary</TargetDataType>
      <Factor>1</Factor>
      <Priority>40</Priority>
      <Add>true</Add>
      <TargetDepth>40</TargetDepth>
      <Condition></Condition>
      <Comment></Comment>
    </Entry>
    <Entry>
      <SourceCode>KorteSchuldenAflossingen</SourceCode>
      <SourceCodeAlias></SourceCodeAlias>
      <SourceFinanVarName>KorteSchuldenAflossingen</SourceFinanVarName>
      <TargetCode>STPartOfLTDebts</TargetCode>
      <TargetCodeAlias></TargetCodeAlias>
      <TargetFinanVarName>STPartOfLTDebts</TargetFinanVarName>
      <TargetDataType>Monetary</TargetDataType>
      <Factor>1</Factor>
      <Priority>40</Priority>
      <Add>true</Add>
      <TargetDepth>40</TargetDepth>
      <Condition></Condition>
      <Comment></Comment>
    </Entry>
    <Entry>
      <SourceCode>KorteSchuldenBelastingSocialeLasten</SourceCode>
      <SourceCodeAlias></SourceCodeAlias>
      <SourceFinanVarName>KorteSchuldenBelastingSocialeLasten</SourceFinanVarName>
      <TargetCode>TaxesAndSocialSecurityCharges</TargetCode>
      <TargetCodeAlias></TargetCodeAlias>
      <TargetFinanVarName>TaxesAndSocialSecurityCharges</TargetFinanVarName>
      <TargetDataType>Monetary</TargetDataType>
      <Factor>1</Factor>
      <Priority>40</Priority>
      <Add>true</Add>
      <TargetDepth>40</TargetDepth>
      <Condition></Condition>
      <Comment></Comment>
    </Entry>
    <Entry>
      <SourceCode>OverigeSchulden</SourceCode>
      <SourceCodeAlias></SourceCodeAlias>
      <SourceFinanVarName>OverigeSchulden</SourceFinanVarName>
      <TargetCode>OtherShortTermDebt</TargetCode>
      <TargetCodeAlias></TargetCodeAlias>
      <TargetFinanVarName>OtherShortTermDebt</TargetFinanVarName>
      <TargetDataType>Monetary</TargetDataType>
      <Factor>1</Factor>
      <Priority>40</Priority>
      <Add>true</Add>
      <TargetDepth>40</TargetDepth>
      <Condition></Condition>
      <Comment></Comment>
    </Entry>
    <Entry>
      <SourceCode>KorteSchuldenKredietinstellingen</SourceCode>
      <SourceCodeAlias></SourceCodeAlias>
      <SourceFinanVarName>KorteSchuldenKredietinstellingen</SourceFinanVarName>
      <TargetCode>OverdraftCurrentAccount</TargetCode>
      <TargetCodeAlias></TargetCodeAlias>
      <TargetFinanVarName>OverdraftCurrentAccount</TargetFinanVarName>
      <TargetDataType>Monetary</TargetDataType>
      <Factor>1</Factor>
      <Priority>40</Priority>
      <Add>true</Add>
      <TargetDepth>40</TargetDepth>
      <Condition></Condition>
      <Comment></Comment>
    </Entry>
    <Entry>
      <SourceCode>AantalFTE</SourceCode>
      <SourceCodeAlias></SourceCodeAlias>
      <SourceFinanVarName>AantalFTE</SourceFinanVarName>
      <TargetCode>Department_tpNumberOfEmployees_ti001</TargetCode>
      <TargetCodeAlias></TargetCodeAlias>
      <TargetFinanVarName>Department_tpNumberOfEmployees_ti001</TargetFinanVarName>
      <TargetDataType>Number</TargetDataType>
      <Factor>1</Factor>
      <Priority>40</Priority>
      <Add>true</Add>
      <TargetDepth>40</TargetDepth>
      <Condition></Condition>
      <Comment></Comment>
    </Entry>
    <Entry>
      <SourceCode>MaterieelVasteActiva</SourceCode>
      <SourceCodeAlias></SourceCodeAlias>
      <SourceFinanVarName>MaterieelVasteActiva</SourceFinanVarName>
      <TargetCode>MaterialFixedAssets</TargetCode>
      <TargetCodeAlias></TargetCodeAlias>
      <TargetFinanVarName>MaterialFixedAssets</TargetFinanVarName>
      <TargetDataType>Monetary</TargetDataType>
      <Factor>1</Factor>
      <Priority>30</Priority>
      <Add>false</Add>
      <TargetDepth>30</TargetDepth>
      <Condition></Condition>
      <Comment></Comment>
    </Entry>
    <Entry>
      <SourceCode>SubtotaalKosten</SourceCode>
      <SourceCodeAlias></SourceCodeAlias>
      <SourceFinanVarName>SubtotaalKosten</SourceFinanVarName>
      <TargetCode>OperatingExpenses</TargetCode>
      <TargetCodeAlias></TargetCodeAlias>
      <TargetFinanVarName>OperatingExpenses</TargetFinanVarName>
      <TargetDataType>Monetary</TargetDataType>
      <Factor>-1</Factor>
      <Priority>30</Priority>
      <Add>false</Add>
      <TargetDepth>30</TargetDepth>
      <Condition></Condition>
      <Comment></Comment>
    </Entry>
    <Entry>
      <SourceCode>Vorderingen</SourceCode>
      <SourceCodeAlias></SourceCodeAlias>
      <SourceFinanVarName>Vorderingen</SourceFinanVarName>
      <TargetCode>Receivables</TargetCode>
      <TargetCodeAlias></TargetCodeAlias>
      <TargetFinanVarName>Receivables</TargetFinanVarName>
      <TargetDataType>Monetary</TargetDataType>
      <Factor>1</Factor>
      <Priority>30</Priority>
      <Add>false</Add>
      <TargetDepth>30</TargetDepth>
      <Condition></Condition>
      <Comment></Comment>
    </Entry>
    <Entry>
      <SourceCode>Voorzieningen</SourceCode>
      <SourceCodeAlias></SourceCodeAlias>
      <SourceFinanVarName>Voorzieningen</SourceFinanVarName>
      <TargetCode>OtherProvisions</TargetCode>
      <TargetCodeAlias></TargetCodeAlias>
      <TargetFinanVarName>OtherProvisions</TargetFinanVarName>
      <TargetDataType>Monetary</TargetDataType>
      <Factor>1</Factor>
      <Priority>40</Priority>
      <Add>true</Add>
      <TargetDepth>40</TargetDepth>
      <Condition></Condition>
      <Comment></Comment>
    </Entry>
    <Entry>
      <SourceCode>VoorzieningenTotaal</SourceCode>
      <SourceCodeAlias></SourceCodeAlias>
      <SourceFinanVarName>VoorzieningenTotaal</SourceFinanVarName>
      <TargetCode>Provisions</TargetCode>
      <TargetCodeAlias></TargetCodeAlias>
      <TargetFinanVarName>Provisions</TargetFinanVarName>
      <TargetDataType>Monetary</TargetDataType>
      <Factor>1</Factor>
      <Priority>30</Priority>
      <Add>false</Add>
      <TargetDepth>30</TargetDepth>
      <Condition></Condition>
      <Comment></Comment>
    </Entry>
    <Entry>
      <SourceCode>LanglopendeSchulden</SourceCode>
      <SourceCodeAlias></SourceCodeAlias>
      <SourceFinanVarName>LanglopendeSchulden</SourceFinanVarName>
      <TargetCode>NonCurrentLiabilities</TargetCode>
      <TargetCodeAlias></TargetCodeAlias>
      <TargetFinanVarName>NonCurrentLiabilities</TargetFinanVarName>
      <TargetDataType>Monetary</TargetDataType>
      <Factor>1</Factor>
      <Priority>30</Priority>
      <Add>false</Add>
      <TargetDepth>30</TargetDepth>
      <Condition></Condition>
      <Comment></Comment>
    </Entry>
    <Entry>
      <SourceCode>KortlopendeSchulden</SourceCode>
      <SourceCodeAlias></SourceCodeAlias>
      <SourceFinanVarName>KortlopendeSchulden</SourceFinanVarName>
      <TargetCode>CurrentLiabilities</TargetCode>
      <TargetCodeAlias></TargetCodeAlias>
      <TargetFinanVarName>CurrentLiabilities</TargetFinanVarName>
      <TargetDataType>Monetary</TargetDataType>
      <Factor>1</Factor>
      <Priority>30</Priority>
      <Add>false</Add>
      <TargetDepth>30</TargetDepth>
      <Condition></Condition>
      <Comment></Comment>
    </Entry>
    <Entry>
      <SourceCode>AfschrijvingDebiteuren</SourceCode>
      <SourceCodeAlias></SourceCodeAlias>
      <SourceFinanVarName>AfschrijvingDebiteuren</SourceFinanVarName>
      <TargetCode>SalesCorrections</TargetCode>
      <TargetCodeAlias></TargetCodeAlias>
      <TargetFinanVarName>SalesCorrections</TargetFinanVarName>
      <TargetDataType>Monetary</TargetDataType>
      <Factor>-1</Factor>
      <Priority>40</Priority>
      <Add>true</Add>
      <TargetDepth>40</TargetDepth>
      <Condition></Condition>
      <Comment></Comment>
    </Entry>
    <Entry>
      <SourceCode>ResultaatBoekjaar</SourceCode>
      <SourceCodeAlias></SourceCodeAlias>
      <SourceFinanVarName>ResultaatBoekjaar</SourceFinanVarName>
      <TargetCode>OtherReserve</TargetCode>
      <TargetCodeAlias></TargetCodeAlias>
      <TargetFinanVarName>OtherReserve</TargetFinanVarName>
      <TargetDataType>Monetary</TargetDataType>
      <Factor>1</Factor>
      <Priority>40</Priority>
      <Add>true</Add>
      <TargetDepth>40</TargetDepth>
      <Condition></Condition>
      <Comment></Comment>
    </Entry>
    <Entry>
      <SourceCode>Huisvestingskosten</SourceCode>
      <SourceCodeAlias></SourceCodeAlias>
      <SourceFinanVarName>Huisvestingskosten</SourceFinanVarName>
      <TargetCode>OfficeExpenses</TargetCode>
      <TargetCodeAlias></TargetCodeAlias>
      <TargetFinanVarName>OfficeExpenses</TargetFinanVarName>
      <TargetDataType>Monetary</TargetDataType>
      <Factor>-1</Factor>
      <Priority>40</Priority>
      <Add>true</Add>
      <TargetDepth>40</TargetDepth>
      <Condition></Condition>
      <Comment></Comment>
    </Entry>
    <Entry>
      <SourceCode>Verkoopkosten</SourceCode>
      <SourceCodeAlias></SourceCodeAlias>
      <SourceFinanVarName>Verkoopkosten</SourceFinanVarName>
      <TargetCode>SellingExpenses</TargetCode>
      <TargetCodeAlias></TargetCodeAlias>
      <TargetFinanVarName>SellingExpenses</TargetFinanVarName>
      <TargetDataType>Monetary</TargetDataType>
      <Factor>-1</Factor>
      <Priority>40</Priority>
      <Add>true</Add>
      <TargetDepth>40</TargetDepth>
      <Condition></Condition>
      <Comment></Comment>
    </Entry>
    <Entry>
      <SourceCode>Vervoerskosten</SourceCode>
      <SourceCodeAlias></SourceCodeAlias>
      <SourceFinanVarName>Vervoerskosten</SourceFinanVarName>
      <TargetCode>TransportationExpenses</TargetCode>
      <TargetCodeAlias></TargetCodeAlias>
      <TargetFinanVarName>TransportationExpenses</TargetFinanVarName>
      <TargetDataType>Monetary</TargetDataType>
      <Factor>-1</Factor>
      <Priority>40</Priority>
      <Add>true</Add>
      <TargetDepth>40</TargetDepth>
      <Condition></Condition>
      <Comment></Comment>
    </Entry>
    <Entry>
      <SourceCode>InventarisMachineKosten</SourceCode>
      <SourceCodeAlias></SourceCodeAlias>
      <SourceFinanVarName>InventarisMachineKosten</SourceFinanVarName>
      <TargetCode>MaintenanceProductionExpenses</TargetCode>
      <TargetCodeAlias></TargetCodeAlias>
      <TargetFinanVarName>MaintenanceProductionExpenses</TargetFinanVarName>
      <TargetDataType>Monetary</TargetDataType>
      <Factor>-1</Factor>
      <Priority>50</Priority>
      <Add>true</Add>
      <TargetDepth>50</TargetDepth>
      <Condition></Condition>
      <Comment></Comment>
    </Entry>
    <Entry>
      <SourceCode>AlgemeneKosten</SourceCode>
      <SourceCodeAlias></SourceCodeAlias>
      <SourceFinanVarName>AlgemeneKosten</SourceFinanVarName>
      <TargetCode>MonitoringAndControlExpense</TargetCode>
      <TargetCodeAlias></TargetCodeAlias>
      <TargetFinanVarName>MonitoringAndControlExpense</TargetFinanVarName>
      <TargetDataType>Monetary</TargetDataType>
      <Factor>-1</Factor>
      <Priority>50</Priority>
      <Add>true</Add>
      <TargetDepth>50</TargetDepth>
      <Condition></Condition>
      <Comment></Comment>
    </Entry>
    <Entry>
      <SourceCode>Automatiseringskosten</SourceCode>
      <SourceCodeAlias></SourceCodeAlias>
      <SourceFinanVarName>Automatiseringskosten</SourceFinanVarName>
      <TargetCode>ContributionsMonitoringAndControlExpenses</TargetCode>
      <TargetCodeAlias></TargetCodeAlias>
      <TargetFinanVarName>ContributionsMonitoringAndControlExpenses</TargetFinanVarName>
      <TargetDataType>Monetary</TargetDataType>
      <Factor>-1</Factor>
      <Priority>50</Priority>
      <Add>true</Add>
      <TargetDepth>50</TargetDepth>
      <Condition></Condition>
      <Comment></Comment>
    </Entry>
    <Entry>
      <SourceCode>KapitaalBV</SourceCode>
      <SourceCodeAlias></SourceCodeAlias>
      <SourceFinanVarName>KapitaalBV</SourceFinanVarName>
      <TargetCode>SharedCapital</TargetCode>
      <TargetCodeAlias></TargetCodeAlias>
      <TargetFinanVarName>SharedCapital</TargetFinanVarName>
      <TargetDataType>Monetary</TargetDataType>
      <Factor>1</Factor>
      <Priority>40</Priority>
      <Add>true</Add>
      <TargetDepth>40</TargetDepth>
      <Condition></Condition>
      <Comment></Comment>
    </Entry>
    <Entry>
      <SourceCode>KapitaalPartners</SourceCode>
      <SourceCodeAlias></SourceCodeAlias>
      <SourceFinanVarName>KapitaalPartners</SourceFinanVarName>
      <TargetCode>Partner_tpCapital_ti001</TargetCode>
      <TargetCodeAlias></TargetCodeAlias>
      <TargetFinanVarName>Partner_tpCapital_ti001</TargetFinanVarName>
      <TargetDataType>Monetary</TargetDataType>
      <Factor>1</Factor>
      <Priority>50</Priority>
      <Add>true</Add>
      <TargetDepth>50</TargetDepth>
      <Condition></Condition>
      <Comment></Comment>
    </Entry>
    <Entry>
      <SourceCode>PriveOpnames</SourceCode>
      <SourceCodeAlias></SourceCodeAlias>
      <SourceFinanVarName>PriveOpnames</SourceFinanVarName>
      <TargetCode>Partner_tpPersonalDrawDown_ti001</TargetCode>
      <TargetCodeAlias></TargetCodeAlias>
      <TargetFinanVarName>Partner_tpPersonalDrawDown_ti001</TargetFinanVarName>
      <TargetDataType>Monetary</TargetDataType>
      <Factor>1</Factor>
      <Priority>40</Priority>
      <Add>true</Add>
      <TargetDepth>40</TargetDepth>
      <Condition></Condition>
      <Comment></Comment>
    </Entry>
    <Entry>
      <SourceCode>PriveOpnames</SourceCode>
      <SourceCodeAlias></SourceCodeAlias>
      <SourceFinanVarName>PriveOpnames</SourceFinanVarName>
      <TargetCode>Partner_tpCapital_ti001</TargetCode>
      <TargetCodeAlias></TargetCodeAlias>
      <TargetFinanVarName>Partner_tpCapital_ti001</TargetFinanVarName>
      <TargetDataType>Monetary</TargetDataType>
      <Factor>1</Factor>
      <Priority>50</Priority>
      <Add>true</Add>
      <TargetDepth>50</TargetDepth>
      <Condition></Condition>
      <Comment></Comment>
    </Entry>
    <Entry>
      <SourceCode>Rechtsvorm</SourceCode>
      <SourceCodeAlias></SourceCodeAlias>
      <SourceFinanVarName>Rechtsvorm</SourceFinanVarName>
      <TargetCode>Rechtsvorm</TargetCode>
      <TargetCodeAlias></TargetCodeAlias>
      <TargetFinanVarName>Rechtsvorm</TargetFinanVarName>
      <TargetDataType>Enumeration</TargetDataType>
      <Factor>1</Factor>
      <Priority>20</Priority>
      <Add>false</Add>
      <TargetDepth>20</TargetDepth>
      <Condition></Condition>
      <Comment></Comment>
    </Entry>
    <Entry>
      <SourceCode>Kantoorkosten</SourceCode>
      <SourceCodeAlias></SourceCodeAlias>
      <SourceFinanVarName>Kantoorkosten</SourceFinanVarName>
      <TargetCode>OtherMonitoringAndControlExpenses</TargetCode>
      <TargetCodeAlias></TargetCodeAlias>
      <TargetFinanVarName>OtherMonitoringAndControlExpenses</TargetFinanVarName>
      <TargetDataType>Monetary</TargetDataType>
      <Factor>-1</Factor>
      <Priority>50</Priority>
      <Add>true</Add>
      <TargetDepth>50</TargetDepth>
      <Condition></Condition>
      <Comment></Comment>
    </Entry>
    <Entry>
      <SourceCode>Bezoeker</SourceCode>
      <SourceCodeAlias></SourceCodeAlias>
      <SourceFinanVarName>Bezoeker</SourceFinanVarName>
      <TargetCode>BBISC_Visit_Visitor</TargetCode>
      <TargetCodeAlias></TargetCodeAlias>
      <TargetFinanVarName>BBISC_Visit_Visitor</TargetFinanVarName>
      <TargetDataType>String</TargetDataType>
      <Factor>1</Factor>
      <Priority>40</Priority>
      <Add>false</Add>
      <TargetDepth>40</TargetDepth>
      <Condition></Condition>
      <Comment></Comment>
    </Entry>
    <Entry>
      <SourceCode>BereikbaarheidScore</SourceCode>
      <SourceCodeAlias></SourceCodeAlias>
      <SourceFinanVarName>BereikbaarheidScore</SourceFinanVarName>
      <TargetCode>BBIVar204</TargetCode>
      <TargetCodeAlias></TargetCodeAlias>
      <TargetFinanVarName>BBIVar204</TargetFinanVarName>
      <TargetDataType>Number</TargetDataType>
      <Factor>1</Factor>
      <Priority>40</Priority>
      <Add>false</Add>
      <TargetDepth>40</TargetDepth>
      <Condition></Condition>
      <Comment></Comment>
    </Entry>
    <Entry>
      <SourceCode>DatumBezoek</SourceCode>
      <SourceCodeAlias></SourceCodeAlias>
      <SourceFinanVarName>DatumBezoek</SourceFinanVarName>
      <TargetCode>BBISC_Visit_Date</TargetCode>
      <TargetCodeAlias></TargetCodeAlias>
      <TargetFinanVarName>BBISC_Visit_Date</TargetFinanVarName>
      <TargetDataType>Date</TargetDataType>
      <Factor>1</Factor>
      <Priority>40</Priority>
      <Add>false</Add>
      <TargetDepth>40</TargetDepth>
      <Condition></Condition>
      <Comment></Comment>
    </Entry>
    <Entry>
      <SourceCode>OndernemerScore</SourceCode>
      <SourceCodeAlias></SourceCodeAlias>
      <SourceFinanVarName>OndernemerScore</SourceFinanVarName>
      <TargetCode>BBIVar203</TargetCode>
      <TargetCodeAlias></TargetCodeAlias>
      <TargetFinanVarName>BBIVar203</TargetFinanVarName>
      <TargetDataType>Number</TargetDataType>
      <Factor>1</Factor>
      <Priority>40</Priority>
      <Add>false</Add>
      <TargetDepth>40</TargetDepth>
      <Condition></Condition>
      <Comment></Comment>
    </Entry>
    <Entry>
      <SourceCode>Oppervlakte</SourceCode>
      <SourceCodeAlias></SourceCodeAlias>
      <SourceFinanVarName>Oppervlakte</SourceFinanVarName>
      <TargetCode>TotalIndoorSpace</TargetCode>
      <TargetCodeAlias></TargetCodeAlias>
      <TargetFinanVarName>TotalIndoorSpace</TargetFinanVarName>
      <TargetDataType>Number</TargetDataType>
      <Factor>1</Factor>
      <Priority>30</Priority>
      <Add>true</Add>
      <TargetDepth>30</TargetDepth>
      <Condition></Condition>
      <Comment></Comment>
    </Entry>
    <Entry>
      <SourceCode>PersoneelScore</SourceCode>
      <SourceCodeAlias></SourceCodeAlias>
      <SourceFinanVarName>PersoneelScore</SourceFinanVarName>
      <TargetCode>BBIVar202</TargetCode>
      <TargetCodeAlias></TargetCodeAlias>
      <TargetFinanVarName>BBIVar202</TargetFinanVarName>
      <TargetDataType>Number</TargetDataType>
      <Factor>1</Factor>
      <Priority>40</Priority>
      <Add>false</Add>
      <TargetDepth>40</TargetDepth>
      <Condition></Condition>
      <Comment></Comment>
    </Entry>
    <Entry>
      <SourceCode>WinkelScore</SourceCode>
      <SourceCodeAlias></SourceCodeAlias>
      <SourceFinanVarName>WinkelScore</SourceFinanVarName>
      <TargetCode>BBIVar201</TargetCode>
      <TargetCodeAlias></TargetCodeAlias>
      <TargetFinanVarName>BBIVar201</TargetFinanVarName>
      <TargetDataType>Number</TargetDataType>
      <Factor>1</Factor>
      <Priority>40</Priority>
      <Add>false</Add>
      <TargetDepth>40</TargetDepth>
      <Condition></Condition>
      <Comment></Comment>
    </Entry>
    <Entry>
      <SourceCode>BenchmarkClass</SourceCode>
      <SourceCodeAlias></SourceCodeAlias>
      <SourceFinanVarName>BenchmarkClass</SourceFinanVarName>
      <TargetCode>BBIBenchmarkClass</TargetCode>
      <TargetCodeAlias></TargetCodeAlias>
      <TargetFinanVarName>BBIBenchmarkClass</TargetFinanVarName>
      <TargetDataType>Enumeration</TargetDataType>
      <Factor>1</Factor>
      <Priority>30</Priority>
      <Add>false</Add>
      <TargetDepth>30</TargetDepth>
      <Condition></Condition>
      <Comment></Comment>
    </Entry>
  </Entries>
</FmtMappingTable>
